{
  "date": "2026-03-13",
  "reference_decision": "2026-03-12",
  "operations": [
    {
      "type": "VENDA",
      "ticker": "LMTB34",
      "qtd": 19,
      "preco": 3368.41
    },
    {
      "type": "VENDA",
      "ticker": "MUTC34",
      "qtd": 73,
      "preco": 347
    }
  ],
  "cash_movements": [],
  "cash_transfers": [],
  "cash_free": 119.86000000000058,
  "cash_accounting": 89330.78999999995,
  "caixa_liquido_real": null,
  "positions_snapshot": [
    {
      "ticker": "AURA33",
      "data_compra": "2026-03-03",
      "qtd": 490,
      "preco_compra": 151
    },
    {
      "ticker": "AURA33",
      "data_compra": "2026-03-11",
      "qtd": 200,
      "preco_compra": 145.34
    },
    {
      "ticker": "BGIP3",
      "data_compra": "2026-03-03",
      "qtd": 1219,
      "preco_compra": 60.77
    },
    {
      "ticker": "BIED3",
      "data_compra": "2026-03-03",
      "qtd": 9815,
      "preco_compra": 7.55
    },
    {
      "ticker": "BIED3",
      "data_compra": "2026-03-11",
      "qtd": 4000,
      "preco_compra": 7.45
    },
    {
      "ticker": "CBAV3",
      "data_compra": "2026-03-03",
      "qtd": 7265,
      "preco_compra": 10.2
    },
    {
      "ticker": "GOLL54",
      "data_compra": "2026-03-03",
      "qtd": 6563,
      "preco_compra": 11.29
    },
    {
      "ticker": "GOLL54",
      "data_compra": "2026-03-07",
      "qtd": 3000,
      "preco_compra": 11.52
    },
    {
      "ticker": "M1RN34",
      "data_compra": "2026-03-03",
      "qtd": 5472,
      "preco_compra": 13.54
    },
    {
      "ticker": "PRIO3",
      "data_compra": "2026-03-04",
      "qtd": 26,
      "preco_compra": 55.12
    },
    {
      "ticker": "PRIO3",
      "data_compra": "2026-03-10",
      "qtd": 1300,
      "preco_compra": 59.39
    }
  ],
  "defensive_quarantine": [],
  "positions": [
    {
      "ticker": "LMTB34",
      "recommended": "VENDA",
      "executed": "VENDI",
      "qtd": 19,
      "preco": 3368.41,
      "source": "recommended"
    },
    {
      "ticker": "MUTC34",
      "recommended": "VENDA",
      "executed": "VENDI",
      "qtd": 73,
      "preco": 347,
      "source": "recommended"
    }
  ],
  "cash_balance": 119.86000000000058,
  "caixa_liquidando": 89330.78999999995
}
